nbpreview/__init__.py
nbpreview/__main__.py
nbpreview/component/__init__.py
nbpreview/component/content/__init__.py
nbpreview/component/content/input.py
nbpreview/component/content/output/__init__.py
nbpreview/component/content/output/error.py
nbpreview/component/content/output/output.py
nbpreview/component/content/output/result/__init__.py
nbpreview/component/content/output/result/display_data.py
nbpreview/component/content/output/result/drawing.py
nbpreview/component/content/output/result/execution_indicator.py
nbpreview/component/content/output/result/latex.py
nbpreview/component/content/output/result/link.py
nbpreview/component/content/output/result/markdown_extensions.py
nbpreview/component/content/output/result/result.py
nbpreview/component/content/output/result/table.py
nbpreview/component/content/output/stream.py
nbpreview/component/markdown.py
nbpreview/component/row.py
nbpreview/data/__init__.py
nbpreview/errors.py
nbpreview/notebook.py
nbpreview/option_values.py
nbpreview/parameters.py
nbpreview/py.typed
nbpreview/templates/vega_template.jinja
nbpreview-0.10.0.dist-info/METADATA
nbpreview-0.10.0.dist-info/WHEEL
nbpreview-0.10.0.dist-info/entry_points.txt
nbpreview-0.10.0.dist-info/licenses/LICENSE
nbpreview-0.10.0.dist-info/RECORD
