Metadata-Version: 2.4
Name: nbpreview
Version: 0.10.0
Summary: nbpreview
License: MIT
License-File: LICENSE
Author: Paulo S. Costa
Author-email: Paulo.S.Costa5@gmail.com
Requires-Python: >=3.11.0,<4.0.0
Classifier: Development Status :: 4 - Beta
Classifier: License :: OSI Approved :: MIT License
Classifier: Programming Language :: Python :: 3
Classifier: Programming Language :: Python :: 3.11
Classifier: Programming Language :: Python :: 3.12
Classifier: Programming Language :: Python :: 3.13
Classifier: Programming Language :: Python :: 3.14
Requires-Dist: Jinja2 (>=3.1.6)
Requires-Dist: Pillow (>=8.3.1,<11.0.0)
Requires-Dist: Pygments (>=2.19.2)
Requires-Dist: click-help-colors (>=0.9.4)
Requires-Dist: html2text (>=2025.4.15)
Requires-Dist: httpx (>=0.28.1,<0.29.0)
Requires-Dist: ipython (>=9.6.0,<10.0.0)
Requires-Dist: lxml (>=6.0.2)
Requires-Dist: markdown-it-py (>=3.0,<4.0)
Requires-Dist: mdit-py-plugins (>=0.5.0)
Requires-Dist: nbformat (>=5.10.4)
Requires-Dist: picharsso (>=2.0.1)
Requires-Dist: pylatexenc (>=2.10)
Requires-Dist: rich (>=14.2.0)
Requires-Dist: term-image (>=0.7.2,<0.8)
Requires-Dist: typer (>=0.19.2,<0.20.0)
Requires-Dist: types-click (>=7.1.8)
Requires-Dist: validators (>=0.35.0,<0.36.0)
Requires-Dist: yarl (>=1.22.0)
Project-URL: Changelog, https://github.com/paw-lu/nbpreview/releases
Project-URL: Documentation, https://nbpreview.readthedocs.io
Project-URL: Homepage, https://github.com/paw-lu/nbpreview
Project-URL: Issues, https://github.com/paw-lu/nbpreview/issues
Project-URL: Repository, https://github.com/paw-lu/nbpreview
